{
    "configurations": [
        {
            "name": "Win32",
            "includePath": [
                "${workspaceFolder}/**",
                "./3rdparty/"
            ],
            "defines": [
                "_DEBUG",
                "UNICODE",
                "_UNICODE"
            ],
            "compilerPath": "C:\\Qt\\Qt5.4.0\\Tools\\mingw491_32\\bin\\gcc.exe",
            "cStandard": "c11",
            "cppStandard": "c++14",
            "intelliSenseMode": "clang-x86"
        }
    ],
    "version": 4
}